k2/__init__.py
k2/h0rn3t.py
k2_h0rn3t-0.1.0.dist-info/licenses/LICENSE.txt
k2_h0rn3t-0.1.0.dist-info/METADATA
k2_h0rn3t-0.1.0.dist-info/WHEEL
k2_h0rn3t-0.1.0.dist-info/top_level.txt
k2_h0rn3t-0.1.0.dist-info/RECORD
