Metadata-Version: 2.4
Name: k2-h0rn3t
Version: 0.1.0
Summary: k2 — a small threaded path scanner (h0rn3t)
Requires-Python: >=3.8
License-File: LICENSE.txt
Requires-Dist: requests
Requires-Dist: colorama
Dynamic: license-file
